OpenFisca_France_Fiscalite_Miniere-5.2.0.data/data/share/openfisca/openfisca-france-fiscalite-miniere/CHANGELOG.md
OpenFisca_France_Fiscalite_Miniere-5.2.0.data/data/share/openfisca/openfisca-france-fiscalite-miniere/LICENSE
OpenFisca_France_Fiscalite_Miniere-5.2.0.data/data/share/openfisca/openfisca-france-fiscalite-miniere/README.md
openfisca_france_fiscalite_miniere/__init__.py
openfisca_france_fiscalite_miniere/entities.py
openfisca_france_fiscalite_miniere/examples/__init__.py
openfisca_france_fiscalite_miniere/examples/article.json
openfisca_france_fiscalite_miniere/examples/nouveau_format.json
openfisca_france_fiscalite_miniere/parameters/frais/taux_assiette_recouvrement.yaml
openfisca_france_fiscalite_miniere/parameters/frais/taux_degrevement_non_valeur.yaml
openfisca_france_fiscalite_miniere/parameters/redevances/communales/antimoine.yaml
openfisca_france_fiscalite_miniere/parameters/redevances/communales/argentifere.yaml
openfisca_france_fiscalite_miniere/parameters/redevances/communales/arsenic.yaml
openfisca_france_fiscalite_miniere/parameters/redevances/communales/aurifere.yaml
openfisca_france_fiscalite_miniere/parameters/redevances/communales/bauxite.yaml
openfisca_france_fiscalite_miniere/parameters/redevances/communales/bismuth.yaml
openfisca_france_fiscalite_miniere/parameters/redevances/communales/bitume_distillation.yaml
openfisca_france_fiscalite_miniere/parameters/redevances/communales/bitume_non_distillation.yaml
openfisca_france_fiscalite_miniere/parameters/redevances/communales/butane.yaml
openfisca_france_fiscalite_miniere/parameters/redevances/communales/charbon.yaml
openfisca_france_fiscalite_miniere/parameters/redevances/communales/cuivre.yaml
openfisca_france_fiscalite_miniere/parameters/redevances/communales/degazolinage.yaml
openfisca_france_fiscalite_miniere/parameters/redevances/communales/etain.yaml
openfisca_france_fiscalite_miniere/parameters/redevances/communales/fer.yaml
OpenFisca_France_Fiscalite_Miniere-5.2.0.dist-info/LICENSE
OpenFisca_France_Fiscalite_Miniere-5.2.0.dist-info/METADATA
OpenFisca_France_Fiscalite_Miniere-5.2.0.dist-info/WHEEL
OpenFisca_France_Fiscalite_Miniere-5.2.0.dist-info/top_level.txt
OpenFisca_France_Fiscalite_Miniere-5.2.0.dist-info/RECORD
